py2pyrecruitment2/__init__.py
py2pyrecruitment2-0.0.5.dist-info/LICENSE.txt
py2pyrecruitment2-0.0.5.dist-info/METADATA
py2pyrecruitment2-0.0.5.dist-info/WHEEL
py2pyrecruitment2-0.0.5.dist-info/top_level.txt
py2pyrecruitment2-0.0.5.dist-info/RECORD
