Metadata-Version: 2.1
Name: py2pyrecruitment2
Version: 0.0.5
Summary: Predicting selection chances
Home-page: https://github.com/mandar196/Recruitment-prediction-system
Author: Mandar kulkarni
Author-email: kulkarnimandar96@gmail.com
License: UNKNOWN
Platform: UNKNOWN
Classifier: Programming Language :: Python :: 3
Classifier: License :: OSI Approved :: MIT License
Classifier: Operating System :: OS Independent
